microsoft_service_wrapper/__init__.py
microsoft_service_wrapper/generic/__init__.py
microsoft_service_wrapper/generic/client.py
microsoft_service_wrapper/ms_graph/__init__.py
microsoft_service_wrapper/ms_graph/client.py
microsoft_service_wrapper/ms_powerbi/__init__.py
microsoft_service_wrapper/ms_powerbi/client.py
microsoft_service_wrapper/ms_powerbi/constants.py
microsoft_service_wrapper-0.4.0.dist-info/AUTHORS.rst
microsoft_service_wrapper-0.4.0.dist-info/LICENSE
microsoft_service_wrapper-0.4.0.dist-info/METADATA
microsoft_service_wrapper-0.4.0.dist-info/WHEEL
microsoft_service_wrapper-0.4.0.dist-info/top_level.txt
microsoft_service_wrapper-0.4.0.dist-info/RECORD
