Metadata-Version: 2.1
Name: microsoft-service-wrapper
Version: 0.4.0
Summary: A python wrapper for microsoft services REST API (currently: Graph and PowerBI)
Home-page: https://github.com/lucas8107/microsoft-service-wrapper
Author: Lucas Paula
Author-email: luolcami@gmail.com
License: MIT license
Keywords: microsoft_service_wrapper
Platform: UNKNOWN
Classifier: Development Status :: 2 - Pre-Alpha
Classifier: Intended Audience :: Developers
Classifier: License :: OSI Approved :: MIT License
Classifier: Natural Language :: English
Classifier: Programming Language :: Python :: 3
Classifier: Programming Language :: Python :: 3.8
Classifier: Programming Language :: Python :: 3.9
Requires-Python: >=3.6
License-File: LICENSE
License-File: AUTHORS.rst
Requires-Dist: msal (~=1.17.0)
Requires-Dist: requests (~=2.27.1)
